cognite_jupyterlab_copilot/__init__.py
cognite_jupyterlab_copilot/_version.py
cognite_jupyterlab_copilot-3.5.10.data/data/share/jupyter/labextensions/cognite_jupyterlab_copilot/package.json
cognite_jupyterlab_copilot-3.5.10.data/data/share/jupyter/labextensions/cognite_jupyterlab_copilot/schemas/cognite_jupyterlab_copilot/button_plugin.json
cognite_jupyterlab_copilot-3.5.10.data/data/share/jupyter/labextensions/cognite_jupyterlab_copilot/schemas/cognite_jupyterlab_copilot/package.json.orig
cognite_jupyterlab_copilot-3.5.10.data/data/share/jupyter/labextensions/cognite_jupyterlab_copilot/static/04e4b7e507bddfd459edd90ef66fec115c3f5e721deb176cc2106a2f345a630a.jpg
cognite_jupyterlab_copilot-3.5.10.data/data/share/jupyter/labextensions/cognite_jupyterlab_copilot/static/0dd24f3d714522301e8d.woff2
cognite_jupyterlab_copilot-3.5.10.data/data/share/jupyter/labextensions/cognite_jupyterlab_copilot/static/114.496b430fa9c1f2a5fc73.js
cognite_jupyterlab_copilot-3.5.10.data/data/share/jupyter/labextensions/cognite_jupyterlab_copilot/static/114.496b430fa9c1f2a5fc73.js.LICENSE.txt
cognite_jupyterlab_copilot-3.5.10.data/data/share/jupyter/labextensions/cognite_jupyterlab_copilot/static/14.d57e4cbf0c38963b9b08.js
cognite_jupyterlab_copilot-3.5.10.data/data/share/jupyter/labextensions/cognite_jupyterlab_copilot/static/152261291c938aa5aad6a56d52b47ffcb893d1c0387e76d7f270a7382ff786d5.woff2
cognite_jupyterlab_copilot-3.5.10.data/data/share/jupyter/labextensions/cognite_jupyterlab_copilot/static/1b498b959e5b7decbf9185803591d25bc1fbf83e798372ed30d32d5c79d82ff6.woff2
cognite_jupyterlab_copilot-3.5.10.data/data/share/jupyter/labextensions/cognite_jupyterlab_copilot/static/1fc710e817738dfe951c.woff2
cognite_jupyterlab_copilot-3.5.10.data/data/share/jupyter/labextensions/cognite_jupyterlab_copilot/static/200.a0fe82e178fe80690359.js
cognite_jupyterlab_copilot-3.5.10.data/data/share/jupyter/labextensions/cognite_jupyterlab_copilot/static/200.a0fe82e178fe80690359.js.LICENSE.txt
cognite_jupyterlab_copilot-3.5.10.dist-info/METADATA
cognite_jupyterlab_copilot-3.5.10.dist-info/WHEEL
cognite_jupyterlab_copilot-3.5.10.dist-info/licenses/LICENSE
cognite_jupyterlab_copilot-3.5.10.dist-info/RECORD
